{
  "data": {
    "_id": "sunAMAuthSAEService",
    "_type": {
      "_id": "sunAMAuthSAEService",
      "collection": false,
      "name": "sunAMAuthSAEService"
    }
  },
  "metadata": {
    "entityId": "sunAMAuthSAEService",
    "entityType": "sunAMAuthSAEService",
    "objectClass": [
      "sunService",
      "top"
    ],
    "ou": [
      "sunAMAuthSAEService"
    ],
    "pathParams": {},
    "realm": "/preprod-Customers",
    "sunServiceID": null,
    "uid": "ou=sunAMAuthSAEService,ou=services,o=preprod-Customers,ou=services,ou=am-config"
  }
}