{
  "data": {
    "_id": "default",
    "_type": {
      "_id": "ScriptingService",
      "collection": false,
      "name": "ScriptingService"
    }
  },
  "metadata": {
    "entityId": "default",
    "entityType": "ScriptingService",
    "objectClass": [
      "sunServiceComponent",
      "top"
    ],
    "ou": [
      "default"
    ],
    "pathParams": {},
    "realm": "/Customers",
    "sunServiceID": null,
    "uid": "ou=default,ou=OrganizationConfig,ou=1.0,ou=ScriptingService,ou=services,o=Customers,ou=services,ou=am-config"
  }
}